BFA/__init__.py
BFA/config.yaml
BFA/io.py
BFA/main.py
BFA/utils.py
BFA/forced_aligner/__init__.py
BFA/forced_aligner/audio_preprocessor.py
BFA/forced_aligner/path_tracer.py
BFA/forced_aligner/inference_engine/__init__.py
BFA/forced_aligner/inference_engine/decoder.py
BFA/forced_aligner/inference_engine/encoder.py
BFA/forced_aligner/inference_engine/joint_network.py
BFA/forced_aligner/inference_engine/weights/bfa_model_decoder_100.pt
BFA/forced_aligner/inference_engine/weights/bfa_model_encoder_100.pt
BFA/forced_aligner/inference_engine/weights/bfa_model_joint_network_100.pt
BFA/forced_aligner/text_preprocessor/__init__.py
BFA/forced_aligner/text_preprocessor/ipa_mapping.json
BFA/forced_aligner/text_preprocessor/tokenizer/__init__.py
BFA/forced_aligner/text_preprocessor/tokenizer/tokenizer.json
BFA/logs/placeholder.txt
bfa-0.1.0.dist-info/licenses/LICENSE
bfa-0.1.0.dist-info/METADATA
bfa-0.1.0.dist-info/WHEEL
bfa-0.1.0.dist-info/entry_points.txt
bfa-0.1.0.dist-info/top_level.txt
bfa-0.1.0.dist-info/RECORD
