Metadata-Version: 2.4
Name: BFA
Version: 0.1.0
Summary: CLI tool for RNN-T based text/audio forced alignment.
Author-email: Picus303 <pilleurc@protonmail.com>
License-Expression: MIT
Requires-Python: >=3.12
License-File: LICENSE
Requires-Dist: torch>=2.6
Requires-Dist: torchaudio>=2.6
Requires-Dist: cyclopts>=3.14
Requires-Dist: misaki==0.9
Requires-Dist: matplotlib>=3.8
Requires-Dist: tqdm>=4.66
Requires-Dist: pyyaml>=6.0
Dynamic: license-file
